python_upsrtc/__init__.py
python_upsrtc/scraper.py
python_upsrtc/session.py
python_upsrtc/errors/__init__.py
python_upsrtc/errors/api_error.py
python_upsrtc/errors/invalid_search_settings.py
python_upsrtc/errors/no_bus_stop_found.py
python_upsrtc/errors/no_journey_found.py
python_upsrtc/models/__init__.py
python_upsrtc/models/bus.py
python_upsrtc/models/busStop.py
python_upsrtc/models/seat.py
python_upsrtc/models/ticket.py
python_upsrtc-0.1.2.dist-info/LICENSE
python_upsrtc-0.1.2.dist-info/METADATA
python_upsrtc-0.1.2.dist-info/WHEEL
python_upsrtc-0.1.2.dist-info/top_level.txt
python_upsrtc-0.1.2.dist-info/RECORD
