Metadata-Version: 2.1
Name: python-upsrtc
Version: 0.1.2
Summary: An unofficial python wrapper for UPSRTC internal API
Home-page: https://github.com/mohdsabahat/python-upsrtc/tree/main
Author: Mohd Sabahat
Author-email: mohdsabahat123@gmail.com
Classifier: Programming Language :: Python :: 3
Classifier: License :: OSI Approved :: MIT License
Classifier: Operating System :: OS Independent
Requires-Python: >=3.6
License-File: LICENSE
